<?xml version='1.0' encoding='UTF-8'?>
<!DOCTYPE sailpoint PUBLIC "sailpoint.dtd" "sailpoint.dtd">
<sailpoint>

<!--
    Orphan Correlation Approval Workflow

    Launched by the OrphanCorrelatorResource REST endpoint when an admin
    clicks "Send for Approval" on an orphan account match.

    Flow depends on orcApprovalTarget:

      "manager"  (default):
        Start -> Validate -> Manager Approval -> Correlate/Reject -> Notify -> Stop

      "identity":
        Start -> Validate -> Identity Confirmation -> Correlate/Reject -> Notify -> Stop

      "both":
        Start -> Validate -> Identity Confirmation -> (if confirmed) Manager Approval
                          -> Correlate/Reject -> Notify -> Stop
        If the identity rejects, the workflow stops (no manager step).

    Type = "IdentityUpdate" so that IIQ stores task results and renders the
    work item in the Approvals tab correctly.
-->

<Workflow explicitTransitions="true"
          libraries="Identity"
          name="Workflow-OrphanCorrelationApproval"
          type="IdentityUpdate">

  <Description>
    Approval workflow for orphan account correlation. Supports three
    approval targets: manager only, identity only, or both (identity
    confirms first, then manager approves). Launched programmatically
    by the OrphanCorrelator plugin.
  </Description>

  <!-- ===== Inputs from REST endpoint ===== -->
  <Variable input="true" name="orcNativeIdentity">
    <Description>Native identity (sAMAccountName) of the orphan account.</Description>
  </Variable>
  <Variable input="true" name="orcApplicationName">
    <Description>IIQ application name the orphan link lives on.</Description>
  </Variable>
  <Variable input="true" name="orcIdentityName">
    <Description>Name of the matched identity to correlate to.</Description>
  </Variable>
  <Variable input="true" name="orcIdentityDisplay">
    <Description>Display name of the matched identity (for messages).</Description>
  </Variable>
  <Variable input="true" name="orcStrategy">
    <Description>Fuzzy match strategy that found this match.</Description>
  </Variable>
  <Variable input="true" name="orcScore">
    <Description>Match score 0-100 from the weighted scoring engine.</Description>
  </Variable>
  <Variable input="true" name="orcMatchDetail">
    <Description>Human-readable description of why the match was made.</Description>
  </Variable>
  <Variable input="true" name="orcRequestedBy">
    <Description>Name of the admin who initiated the approval request.</Description>
  </Variable>
  <Variable input="true" name="orcApprovalTarget" initializer="manager">
    <Description>Who must approve: "manager", "identity", or "both".</Description>
  </Variable>
  <Variable input="true" name="orcFallbackApproverGroup" initializer="ServiceAccount-Approvers">
    <Description>
      Name of the workgroup that owns the manager-approval work item when no
      manager can be resolved or the manager would be the requester (no
      self-approval). Must exist as a workgroup Identity; imported by the
      plugin as "ServiceAccount-Approvers".
    </Description>
  </Variable>

  <!-- Resolved during execution -->
  <Variable name="managerName">
    <Description>Name of the line manager who will own the manager work item.</Description>
  </Variable>
  <Variable name="orcAccountSummary">
    <Description>Human-readable summary of the orphan account.</Description>
  </Variable>
  <Variable name="approved">
    <Description>Boolean set by IIQ when an approver actions the work item.</Description>
  </Variable>
  <Variable name="identityConfirmed">
    <Description>Boolean set by the Identity Confirmation step.</Description>
  </Variable>
  <Variable name="orcDecisionComments">
    <Description>Free-text comment from the approver.</Description>
  </Variable>
  <Variable name="orcIdentityComments">
    <Description>Free-text comment from the identity confirmation step.</Description>
  </Variable>
  <Variable name="correlationSuccess">
    <Description>Whether the correlation step succeeded.</Description>
  </Variable>
  <Variable initializer="false" name="trace">
    <Description>If true, workflow trace is written to stdout for debugging.</Description>
  </Variable>

  <!-- ===== STEP 1: Start ===== -->
  <Step icon="Start" name="Start" posX="20" posY="120">
    <Transition to="Validate Inputs"/>
  </Step>

  <!-- ===== STEP 2: Validate Inputs ===== -->
  <Step name="Validate Inputs" posX="140" posY="120">
    <Script>
      <Source><![CDATA[
        import sailpoint.object.Identity;
        import org.apache.log4j.Logger;

        Logger log = Logger.getLogger("com.orphancorrelator.workflow.OrphanCorrelationApproval");

        log.info("OrphanCorrelationApproval: validate inputs."
                 + " nativeIdentity=[" + orcNativeIdentity + "]"
                 + " applicationName=[" + orcApplicationName + "]"
                 + " identityName=[" + orcIdentityName + "]"
                 + " approvalTarget=[" + orcApprovalTarget + "]"
                 + " requestedBy=[" + orcRequestedBy + "]");

        // Fallback owner is the configured workgroup - NEVER the requester
        // (self-approval must be impossible). If the workgroup does not resolve,
        // fail closed to spadmin so the work item still lands with an admin.
        String fallbackApprover = orcFallbackApproverGroup;
        Identity fallbackGroup = null;
        if (fallbackApprover != null && fallbackApprover.length() > 0) {
            fallbackGroup = context.getObjectByName(Identity.class, fallbackApprover);
        }
        if (fallbackGroup == null) {
            log.error("OrphanCorrelationApproval: fallback approver workgroup [" + fallbackApprover
                     + "] does not exist - approvals without a resolvable manager will fail closed"
                     + " to spadmin. Import Workgroup-ServiceAccountApprovers.xml or set the"
                     + " orcFallbackApproverGroup variable to an existing workgroup.");
            fallbackApprover = "spadmin";
        }
        // NOTE: do NOT decache the workgroup here. This script runs inside the
        // launching REST request's Hibernate session; the same Identity is
        // re-loaded moments later as the Approval owner. Evicting it leaves a
        // stale instance referenced by the session and the commit fails with
        // "A different object with the same identifier value was already
        // associated with the session".

        if (orcIdentityName == null || orcIdentityName.length() == 0) {
            log.error("OrphanCorrelationApproval: orcIdentityName is null. Routing approval to fallback ["
                     + fallbackApprover + "].");
            managerName = fallbackApprover;
            return;
        }

        Identity matched = context.getObjectByName(Identity.class, orcIdentityName);
        if (matched == null) {
            log.warn("OrphanCorrelationApproval: identity [" + orcIdentityName
                     + "] not found. Routing approval to fallback [" + fallbackApprover + "].");
            managerName = fallbackApprover;
            return;
        }

        Identity manager = matched.getManager();
        if (manager == null) {
            log.warn("OrphanCorrelationApproval: identity [" + orcIdentityName
                     + "] has no manager. Routing approval to fallback [" + fallbackApprover + "].");
            managerName = fallbackApprover;
        } else if (manager.getName() != null && manager.getName().equals(orcRequestedBy)) {
            log.warn("OrphanCorrelationApproval: resolved manager [" + manager.getName()
                     + "] is the requester - routing to fallback [" + fallbackApprover
                     + "] to prevent self-approval.");
            managerName = fallbackApprover;
        } else {
            managerName = manager.getName();
            log.info("OrphanCorrelationApproval: resolved manager [" + managerName
                     + "] for matched identity [" + orcIdentityName + "].");
        }

        // No decache of `matched` either - same session-eviction hazard as above.
        // The matched identity is the Identity Confirmation owner on the
        // identity/both paths and gets re-loaded during launch.

        orcAccountSummary = "(account detail unavailable)";
        try {
            sailpoint.object.Rule sumRule = context.getObjectByName(sailpoint.object.Rule.class, "Rule-OrphanAccountSummary");
            if (sumRule != null) {
                java.util.HashMap ra = new java.util.HashMap();
                ra.put("nativeIdentity", orcNativeIdentity);
                ra.put("applicationName", orcApplicationName);
                Object res = context.runRule(sumRule, ra);
                if (res != null && res.toString().length() > 0) { orcAccountSummary = res.toString(); }
            }
        } catch (Exception sex) {
            log.warn("OrphanCorrelationApproval: account summary build failed. " + sex.getMessage());
        }
      ]]></Source>
    </Script>
    <!-- Route based on approvalTarget -->
    <Transition to="Identity Confirmation">
      <Script>
        <Source><![CDATA[
          return "identity".equals(orcApprovalTarget) || "both".equals(orcApprovalTarget);
        ]]></Source>
      </Script>
    </Transition>
    <Transition to="Manager Approval"/>
  </Step>

  <!-- ===== STEP 3a: Identity Confirmation =====
       The matched identity confirms "yes, that is my account".
       Used when approvalTarget = "identity" or "both". -->
  <Step icon="Approval" name="Identity Confirmation" posX="280" posY="60">
    <!-- NOTE (work item expiration): the local IIQ 8.5 references do not document
         an expiration Arg for workflow <Approval> steps, so none is set here to
         avoid relying on an unverified mechanism. See the matching note on the
         Manager Approval step. -->
    <Approval mode="serial"
              return="identityConfirmed"
              owner="script:return orcIdentityName;"
              send="orcNativeIdentity,orcApplicationName,orcIdentityName,orcIdentityDisplay,orcStrategy,orcScore,orcMatchDetail,orcAccountSummary">
      <Arg name="workItemType" value="Approval"/>
      <Arg name="workItemDescription">
        <Script>
          <Source><![CDATA[
            return "Please confirm: is account [" + orcNativeIdentity
                   + "] on [" + orcApplicationName + "] yours?";
          ]]></Source>
        </Script>
      </Arg>
      <Arg name="workItemNotificationTemplate"
           value="Orphan Correlation Approval Request"/>
      <Arg name="workItemRequester" value="ref:orcRequestedBy"/>

      <Form>
        <Attributes>
          <Map>
            <entry key="title" value="Account Ownership Confirmation"/>
            <entry key="subtitle" value="An administrator believes this account belongs to you. Please confirm or reject."/>
          </Map>
        </Attributes>
        <Section name="orcIdConfirmAccountSection" label="Account in Question" type="datatable">
          <Field name="orcNativeIdentity"  displayName="Account name"/>
          <Field name="orcApplicationName" displayName="Application"/>
          <Field name="orcAccountSummary"  displayName="Account details"/>
        </Section>
        <Section name="orcIdConfirmMatchSection" label="Match Details" type="datatable">
          <Field name="orcScore"       displayName="Confidence score (out of 100)"/>
          <Field name="orcMatchDetail" displayName="Why we think this is yours"/>
        </Section>
        <Button action="next"   label="Yes - this is my account"/>
        <Button action="back"   label="No - this is not mine"/>
        <Button action="cancel" label="Back"/>
      </Form>

      <AfterScript>
        <Source><![CDATA[
          try {
              if (item != null && item.getCompletionComments() != null) {
                  orcIdentityComments = item.getCompletionComments();
              }
          } catch (Throwable t) { /* best-effort */ }
        ]]></Source>
      </AfterScript>
    </Approval>
    <!-- If identity confirmed AND target is "both", proceed to manager -->
    <Transition to="Manager Approval">
      <Script>
        <Source><![CDATA[
          return Boolean.TRUE.equals(identityConfirmed) && "both".equals(orcApprovalTarget);
        ]]></Source>
      </Script>
    </Transition>
    <!-- If identity confirmed AND target is "identity" only, correlate directly -->
    <Transition to="Correlate Account">
      <Script>
        <Source><![CDATA[
          return Boolean.TRUE.equals(identityConfirmed) && "identity".equals(orcApprovalTarget);
        ]]></Source>
      </Script>
    </Transition>
    <!-- Identity rejected -->
    <Transition to="Reject Correlation"/>
  </Step>

  <!-- ===== STEP 3b: Manager Approval =====
       Used when approvalTarget = "manager" or "both" (after identity confirms). -->
  <Step icon="Approval" name="Manager Approval" posX="420" posY="120">
    <!-- NOTE (work item expiration): the local IIQ 8.5 references do not document
         an expiration Arg for workflow <Approval> steps, so none is set here to
         avoid relying on an unverified mechanism. If unactioned approvals must
         expire, configure work item expiration/escalation via the documented
         global work item settings, or verify the correct Approval Arg against
         controlled SailPoint sources before adding it. -->
    <!-- Owner MUST stay in the owner="script:..." attribute form: an Arg-based
         owner silently auto-approves with no work item (lab-verified).
         managerName is the single source of truth, resolved (with fallback and
         no-self-approve handling) in the Validate Inputs step. The script only
         re-verifies resolvability and fails closed to spadmin. -->
    <Approval mode="serial"
              return="approved"
              owner="script:import sailpoint.object.Identity; org.apache.log4j.Logger olog=org.apache.log4j.Logger.getLogger(&quot;com.orphancorrelator.workflow.OrphanCorrelationApproval&quot;); String o=null; if(orcIdentityName!=null){ Identity m=context.getObjectByName(Identity.class,orcIdentityName); Identity mgr=(m!=null)?m.getManager():null; int level=0; while(mgr!=null &amp;&amp; level&lt;2){ level++; String mn=mgr.getName(); if(mgr.isInactive()){ olog.warn(&quot;OrphanCorrelationApproval: manager [&quot;+mn+&quot;] (level &quot;+level+&quot;) is inactive - escalating to their manager.&quot;); mgr=mgr.getManager(); continue; } if(mn!=null &amp;&amp; mn.equals(orcRequestedBy)){ olog.warn(&quot;OrphanCorrelationApproval: manager [&quot;+mn+&quot;] (level &quot;+level+&quot;) is the requester - skipping to prevent self-approval.&quot;); mgr=mgr.getManager(); continue; } o=mn; break; } } if(o==null){ olog.warn(&quot;OrphanCorrelationApproval: no active non-requester manager found within 2 levels for [&quot;+orcIdentityName+&quot;] - routing to fallback [&quot;+orcFallbackApproverGroup+&quot;].&quot;); o=orcFallbackApproverGroup; } if(o==null || context.getObjectByName(Identity.class,o)==null){ olog.error(&quot;OrphanCorrelationApproval: approval owner [&quot;+o+&quot;] does not resolve - failing closed to spadmin.&quot;); o=&quot;spadmin&quot;; } return o;"
              send="orcNativeIdentity,orcApplicationName,orcIdentityName,orcIdentityDisplay,orcStrategy,orcScore,orcMatchDetail,orcAccountSummary,orcIdentityComments">
      <Arg name="workItemType" value="Approval"/>
      <Arg name="workItemDescription">
        <Script>
          <Source><![CDATA[
            import sailpoint.object.*;
            import java.util.*;
            String base = "Approve correlation of orphan account [" + orcNativeIdentity
                          + "] to identity [" + orcIdentityDisplay + "]";
            if ("both".equals(orcApprovalTarget) && Boolean.TRUE.equals(identityConfirmed)) {
                base = base + " (identity has confirmed ownership)";
            }
            String summary = "";
            try {
                Rule sumRule = context.getObjectByName(Rule.class, "Rule-OrphanAccountSummary");
                if (sumRule != null) {
                    HashMap ra = new HashMap();
                    ra.put("nativeIdentity", orcNativeIdentity);
                    ra.put("applicationName", orcApplicationName);
                    Object res = context.runRule(sumRule, ra);
                    if (res != null) { summary = res.toString(); }
                }
            } catch (Exception e) { /* fall back to base description */ }
            return (summary != null && summary.length() > 0) ? (base + " -- " + summary) : base;
          ]]></Source>
        </Script>
      </Arg>
      <Arg name="workItemNotificationTemplate"
           value="Orphan Correlation Approval Request"/>
      <Arg name="workItemRequester" value="ref:orcRequestedBy"/>

      <Form>
        <Attributes>
          <Map>
            <entry key="title" value="Orphan Account Correlation Approval"/>
            <entry key="subtitle" value="Approve to link this account to the suggested identity. Reject to leave it uncorrelated."/>
          </Map>
        </Attributes>
        <Section name="orcAccountSection" label="Orphan Account" type="datatable">
          <Field name="orcNativeIdentity"  displayName="Account"/>
          <Field name="orcApplicationName" displayName="Application"/>
          <Field name="orcAccountSummary"  displayName="Account details"/>
        </Section>
        <Section name="orcMatchSection" label="Suggested Identity" type="datatable">
          <Field name="orcIdentityDisplay" displayName="Identity"/>
          <Field name="orcIdentityName"    displayName="Identity login"/>
          <Field name="orcStrategy"        displayName="Match strategy"/>
        </Section>
        <Section name="orcConfidenceSection" label="Match Confidence" type="datatable">
          <Field name="orcScore"       displayName="Score (out of 100)"/>
          <Field name="orcMatchDetail" displayName="Match reasons"/>
        </Section>
        <Section name="orcIdentityConfSection" label="Identity Confirmation" type="datatable">
          <Field name="orcIdentityComments" displayName="Identity's comment"/>
        </Section>
        <Button action="next"   label="Approve - link account"/>
        <Button action="back"   label="Reject - leave uncorrelated"/>
        <Button action="cancel" label="Back"/>
      </Form>

      <AfterScript>
        <Source><![CDATA[
          try {
              if (item != null && item.getCompletionComments() != null) {
                  orcDecisionComments = item.getCompletionComments();
              }
          } catch (Throwable t) { /* comment capture is best-effort */ }
        ]]></Source>
      </AfterScript>
    </Approval>
    <Transition to="Correlate Account">
      <Script>
        <Source><![CDATA[
          return Boolean.TRUE.equals(approved);
        ]]></Source>
      </Script>
    </Transition>
    <Transition to="Reject Correlation"/>
  </Step>

  <!-- ===== STEP 4a: Correlate Account (APPROVED branch) ===== -->
  <Step name="Correlate Account" posX="560" posY="60">
    <Script>
      <Source><![CDATA[
        import sailpoint.object.Identity;
        import sailpoint.object.Link;
        import sailpoint.object.QueryOptions;
        import sailpoint.object.Filter;
        import sailpoint.object.WorkItem;
        import org.apache.log4j.Logger;
        import java.util.Iterator;

        Logger log = Logger.getLogger("com.orphancorrelator.workflow.OrphanCorrelationApproval");

        correlationSuccess = Boolean.FALSE;

        if (orcNativeIdentity == null || orcApplicationName == null || orcIdentityName == null) {
            log.error("OrphanCorrelationApproval: missing required variables for correlation.");
            return;
        }

        Identity matchedIdentity = null;
        Link orphanLink          = null;

        try {
            matchedIdentity = context.getObjectByName(Identity.class, orcIdentityName);
            if (matchedIdentity == null) {
                log.error("OrphanCorrelationApproval: identity not found: [" + orcIdentityName + "]");
                return;
            }
            if (!Boolean.TRUE.equals(matchedIdentity.isCorrelated())) {
                log.warn("OrphanCorrelationApproval: target identity [" + orcIdentityName
                         + "] is no longer correlated. Aborting correlation.");
                return;
            }

            QueryOptions qo = new QueryOptions();
            qo.addFilter(Filter.eq("nativeIdentity", orcNativeIdentity));
            qo.addFilter(Filter.eq("application.name", orcApplicationName));
            qo.addFilter(Filter.notnull("identity"));
            qo.addFilter(Filter.eq("identity.correlated", Boolean.FALSE));

            Iterator linkIter = context.search(Link.class, qo);
            try {
                if (linkIter != null && linkIter.hasNext()) {
                    orphanLink = (Link) linkIter.next();
                }
            } finally {
                sailpoint.tools.Util.flushIterator(linkIter);
            }

            if (orphanLink == null) {
                log.warn("OrphanCorrelationApproval: orphan link [" + orcNativeIdentity
                         + "] on [" + orcApplicationName
                         + "] no longer owned by an uncorrelated dummy. Aborting.");
                return;
            }

            String dummyName = (orphanLink.getIdentity() != null)
                    ? orphanLink.getIdentity().getName() : null;

            orphanLink.setIdentity(matchedIdentity);
            context.saveObject(orphanLink);
            context.saveObject(matchedIdentity);
            context.commitTransaction();

            correlationSuccess = Boolean.TRUE;

            String approvedBy = "both".equals(orcApprovalTarget) ? "identity + manager"
                              : ("identity".equals(orcApprovalTarget) ? "identity" : "manager");
            log.info("OrphanCorrelationApproval: correlated [" + orcNativeIdentity
                     + "] to identity [" + orcIdentityName + "] via " + approvedBy + " approval.");

            try {
                if (dummyName != null) {
                    Identity dummy = context.getObjectByName(Identity.class, dummyName);
                    boolean deleted = false;
                    if (dummy != null && Boolean.FALSE.equals(dummy.isCorrelated())) {
                        QueryOptions remQo = new QueryOptions();
                        remQo.addFilter(Filter.eq("identity.name", dummyName));
                        int remaining = context.countObjects(Link.class, remQo);
                        if (remaining == 0) {
                            boolean safe = true;
                            QueryOptions mgrQo = new QueryOptions();
                            mgrQo.addFilter(Filter.eq("manager.name", dummyName));
                            if (context.countObjects(Identity.class, mgrQo) > 0) { safe = false; }
                            if (safe) {
                                QueryOptions wiOwnerQo = new QueryOptions();
                                wiOwnerQo.addFilter(Filter.eq("owner.name", dummyName));
                                if (context.countObjects(WorkItem.class, wiOwnerQo) > 0) { safe = false; }
                            }
                            if (safe) {
                                QueryOptions wiReqQo = new QueryOptions();
                                wiReqQo.addFilter(Filter.eq("requester.name", dummyName));
                                if (context.countObjects(WorkItem.class, wiReqQo) > 0) { safe = false; }
                            }
                            if (safe) {
                                log.info("OrphanCorrelationApproval: deleting empty dummy [" + dummyName + "].");
                                context.removeObject(dummy);
                                context.commitTransaction();
                                deleted = true;
                            } else {
                                log.warn("OrphanCorrelationApproval: dummy [" + dummyName
                                         + "] has 0 links but owns other relationships. Skipping deletion.");
                            }
                        }
                    }
                    if (dummy != null && !deleted) { try { context.decache(dummy); } catch (Exception ignore) {} }
                }
            } catch (Exception delEx) {
                log.warn("OrphanCorrelationApproval: dummy cleanup failed for [" + dummyName
                         + "] (correlation already succeeded). " + delEx.getMessage());
            }

            try {
                sailpoint.object.AuditEvent ev = new sailpoint.object.AuditEvent();
                ev.setSource(orcRequestedBy != null ? orcRequestedBy : "OrphanCorrelator");
                ev.setAction("OrphanCorrelate");
                ev.setTarget(orcNativeIdentity);
                ev.setApplication(orcApplicationName);
                ev.setString1(orcIdentityName);
                ev.setString2(orcScore);
                String auditNote = "Approved via " + orcApprovalTarget + " workflow";
                if (orcIdentityComments != null) { auditNote = auditNote + ". Identity comment: " + orcIdentityComments; }
                if (orcDecisionComments != null) { auditNote = auditNote + ". Manager comment: " + orcDecisionComments; }
                ev.setString3(auditNote);
                context.saveObject(ev);
                context.commitTransaction();
            } catch (Exception aex) {
                log.warn("OrphanCorrelationApproval: approval audit event failed. " + aex.getMessage());
            }

            try {
                sailpoint.object.Attributes rargs = new sailpoint.object.Attributes();
                rargs.put(sailpoint.api.Identitizer.ARG_PROMOTE_ATTRIBUTES,     Boolean.TRUE);
                rargs.put(sailpoint.api.Identitizer.ARG_CORRELATE_ENTITLEMENTS, Boolean.TRUE);
                rargs.put(sailpoint.api.Identitizer.ARG_REFRESH_LINKS,          Boolean.TRUE);
                sailpoint.api.Identitizer idz = new sailpoint.api.Identitizer(context, rargs);
                idz.setRefreshSource(sailpoint.object.Source.Workflow, "OrphanCorrelator");
                Identity toRefresh = context.getObjectByName(Identity.class, orcIdentityName);
                if (toRefresh != null) { idz.refresh(toRefresh); context.commitTransaction(); context.decache(toRefresh); }
            } catch (Exception rex) {
                log.warn("OrphanCorrelationApproval: post-approval refresh failed for ["
                         + orcIdentityName + "]. " + rex.getMessage());
            }

        } catch (Exception ex) {
            log.error("OrphanCorrelationApproval: correlation failed for ["
                      + orcNativeIdentity + "]. Error: " + ex.getMessage());
        } finally {
            if (orphanLink      != null) { try { context.decache(orphanLink);      } catch (Exception ignore) {} }
            if (matchedIdentity != null) { try { context.decache(matchedIdentity); } catch (Exception ignore) {} }
        }
      ]]></Source>
    </Script>
    <Transition to="Notify Admin"/>
  </Step>

  <!-- ===== STEP 4b: Reject Correlation ===== -->
  <Step name="Reject Correlation" posX="560" posY="180">
    <Script>
      <Source><![CDATA[
        import org.apache.log4j.Logger;
        Logger log = Logger.getLogger("com.orphancorrelator.workflow.OrphanCorrelationApproval");
        correlationSuccess = Boolean.FALSE;

        String rejectedBy = "manager";
        String comment = orcDecisionComments;
        Object decisionVar = approved;
        if (!Boolean.TRUE.equals(identityConfirmed) && ("identity".equals(orcApprovalTarget) || "both".equals(orcApprovalTarget))) {
            rejectedBy = "identity";
            comment = orcIdentityComments;
            decisionVar = identityConfirmed;
        }

        // null decision variable = the work item expired or errored without ever
        // being actioned; that is NOT the same as an explicit rejection and the
        // audit trail must say so.
        boolean explicitReject = Boolean.FALSE.equals(decisionVar);
        String auditVerdict = explicitReject
                ? ("Rejected by " + rejectedBy)
                : ("Expired or not actioned (no decision recorded from " + rejectedBy + ")");

        log.info("OrphanCorrelationApproval: correlation of [" + orcNativeIdentity
                 + "] to identity [" + orcIdentityName + "] NOT applied - " + auditVerdict
                 + ". Account remains uncorrelated.");

        try {
            sailpoint.object.AuditEvent ev = new sailpoint.object.AuditEvent();
            ev.setSource(orcRequestedBy != null ? orcRequestedBy : "OrphanCorrelator");
            ev.setAction("OrphanCorrelateRejected");
            ev.setTarget(orcNativeIdentity);
            ev.setApplication(orcApplicationName);
            ev.setString1(orcIdentityName);
            ev.setString2(orcScore);
            ev.setString3(auditVerdict
                    + (comment != null ? (". Comment: " + comment) : ""));
            context.saveObject(ev);
            context.commitTransaction();
        } catch (Exception aex) {
            log.warn("OrphanCorrelationApproval: reject audit event failed. " + aex.getMessage());
        }
      ]]></Source>
    </Script>
    <Transition to="Notify Admin"/>
  </Step>

  <!-- ===== STEP 5: Notify Admin ===== -->
  <Step name="Notify Admin" posX="700" posY="120">
    <Script>
      <Source><![CDATA[
        import sailpoint.object.Identity;
        import sailpoint.object.EmailTemplate;
        import sailpoint.object.EmailOptions;
        import org.apache.log4j.Logger;
        import java.util.HashMap;

        Logger log = Logger.getLogger("com.orphancorrelator.workflow.OrphanCorrelationApproval");

        if (orcRequestedBy == null) {
            log.warn("OrphanCorrelationApproval: no orcRequestedBy - skipping admin notification.");
            return;
        }

        Identity admin = null;
        try {
            admin = context.getObjectByName(Identity.class, orcRequestedBy);
            if (admin == null || admin.getEmail() == null) {
                log.warn("OrphanCorrelationApproval: admin [" + orcRequestedBy
                         + "] not found or has no email. Skipping notification.");
                return;
            }

            EmailTemplate template = context.getObjectByName(EmailTemplate.class,
                                        "Orphan Correlation Result");
            if (template == null) {
                log.warn("OrphanCorrelationApproval: email template [Orphan Correlation"
                         + " Result] not found. Skipping notification.");
                return;
            }

            boolean wasApproved = ("identity".equals(orcApprovalTarget) && Boolean.TRUE.equals(identityConfirmed))
                               || (!"identity".equals(orcApprovalTarget) && Boolean.TRUE.equals(approved));
            boolean correlated  = Boolean.TRUE.equals(correlationSuccess);

            String decision = wasApproved ? "APPROVED" : "REJECTED";
            String outcome;
            if (wasApproved && correlated) {
                outcome = "Correlation completed successfully.";
            } else if (wasApproved) {
                outcome = "Approved but correlation failed or could not be applied - check logs.";
            } else {
                outcome = "Rejected. Account remains uncorrelated.";
            }

            String allComments = "";
            if (orcIdentityComments != null && orcIdentityComments.length() > 0) {
                allComments = "Identity: " + orcIdentityComments;
            }
            if (orcDecisionComments != null && orcDecisionComments.length() > 0) {
                if (allComments.length() > 0) { allComments = allComments + " | "; }
                allComments = allComments + "Manager: " + orcDecisionComments;
            }
            if (allComments.length() == 0) { allComments = "(none)"; }

            HashMap args = new HashMap();
            args.put("adminDisplayName",    admin.getDisplayName());
            args.put("nativeIdentity",      orcNativeIdentity);
            args.put("identityDisplayName", orcIdentityDisplay);
            args.put("decision",            decision);
            args.put("outcome",             outcome);
            args.put("strategy",            orcStrategy);
            args.put("score",               orcScore);
            args.put("comments",            allComments);

            EmailOptions opts = new EmailOptions(admin.getEmail(), args);
            context.sendEmailNotification(template, opts);

            log.info("OrphanCorrelationApproval: result notification sent to admin ["
                     + orcRequestedBy + "] decision=[" + decision + "] target=[" + orcApprovalTarget + "]");

        } catch (Exception ex) {
            log.error("OrphanCorrelationApproval: admin notification failed. Error: " + ex.getMessage());
        } finally {
            if (admin != null) { try { context.decache(admin); } catch (Exception ignore) {} }
        }
      ]]></Source>
    </Script>
    <Transition to="Stop"/>
  </Step>

  <Step icon="Stop" name="Stop" posX="820" posY="120"/>

</Workflow>

  <!-- Shared helper rule (unchanged) -->
  <Rule language="beanshell" name="Rule-OrphanAccountSummary">
    <Description>Builds a one-line orphan-account summary (status, last login, sample access) for the orphan correlation approval. Inputs: nativeIdentity, applicationName.</Description>
    <Signature returnType="String">
      <Inputs>
        <Argument name="nativeIdentity" type="String"/>
        <Argument name="applicationName" type="String"/>
      </Inputs>
      <Returns>
        <Argument name="summary" type="String"/>
      </Returns>
    </Signature>
    <Source><![CDATA[
      import sailpoint.object.*;
      import java.util.*;

      if (nativeIdentity == null || applicationName == null) { return ""; }

      QueryOptions lqo = new QueryOptions();
      lqo.addFilter(Filter.eq("nativeIdentity", nativeIdentity));
      lqo.addFilter(Filter.eq("application.name", applicationName));
      Iterator lit = context.search(Link.class, lqo);
      Link lk = null;
      try { if (lit != null && lit.hasNext()) { lk = (Link) lit.next(); } }
      finally { sailpoint.tools.Util.flushIterator(lit); }
      if (lk == null) { return ""; }

      StringBuilder sum = new StringBuilder();
      sum.append("Status: ").append(lk.isDisabled() ? "Disabled" : (lk.isLocked() ? "Locked" : "Active"));

      String[] llAttrs = { "lastLogon", "lastLogin", "lastLogonTimestamp", "lastSignIn", "pwdLastSet" };
      for (int i = 0; i < llAttrs.length; i++) {
          Object v = lk.getAttribute(llAttrs[i]);
          if (v != null) {
              String s = v.toString().trim();
              boolean dateLike = (s.indexOf('-') >= 0 || s.indexOf('/') >= 0 || s.indexOf(':') >= 0);
              if (s.length() > 0 && !s.equals("0") && dateLike) {
                  sum.append(" | Last login: ").append(s);
              }
              break;
          }
      }

      Attributes ents = lk.getEntitlementAttributes();
      if (ents != null && !ents.isEmpty()) {
          int MAX_SHOWN = 6;
          int total = 0;
          List names = new ArrayList();
          for (Iterator ki = ents.keySet().iterator(); ki.hasNext(); ) {
              Object val = ents.get(ki.next());
              List vals = (val instanceof List) ? (List) val : Collections.singletonList(val);
              for (int j = 0; j < vals.size(); j++) {
                  if (vals.get(j) == null) { continue; }
                  total++;
                  if (names.size() < MAX_SHOWN) {
                      String e = vals.get(j).toString().trim();
                      int comma = e.indexOf(',');
                      String first = (comma > 0) ? e.substring(0, comma) : e;
                      int eq = first.indexOf('=');
                      if (eq >= 0) { first = first.substring(eq + 1); }
                      names.add(first.trim());
                  }
              }
          }
          if (total > 0) {
              StringBuilder eb = new StringBuilder();
              for (int i = 0; i < names.size(); i++) {
                  if (eb.length() > 0) { eb.append(", "); }
                  eb.append(names.get(i));
              }
              if (total > names.size()) { eb.append(", +").append(total - names.size()).append(" more"); }
              sum.append(" | Access: ").append(eb.toString());
          }
      }

      context.decache(lk);
      return sum.toString();
    ]]></Source>
  </Rule>

</sailpoint>
